sf10020uno/Biseccion.py
sf10020uno/Cramer.py
sf10020uno/Descomposicion_LU.py
sf10020uno/Gauss.py
sf10020uno/Gauss_Jordan.py
sf10020uno/Gauss_Seidel.py
sf10020uno/Jacobi.py
sf10020uno/Resolver.py
sf10020uno/__init__.py
sf10020uno-0.1.7.dist-info/licenses/LICENSE
sf10020uno-0.1.7.dist-info/METADATA
sf10020uno-0.1.7.dist-info/WHEEL
sf10020uno-0.1.7.dist-info/top_level.txt
sf10020uno-0.1.7.dist-info/RECORD
