Metadata-Version: 2.4
Name: SF10020UNO
Version: 0.1.7
Summary: Librería para resolver sistemas de ecuaciones lineales y no lineales
Author: Carlos Manuel Solís Flores
Classifier: Programming Language :: Python :: 3
Classifier: License :: OSI Approved :: MIT License
Classifier: Operating System :: OS Independent
Requires-Python: >=3.6
License-File: LICENSE
Requires-Dist: numpy
Dynamic: author
Dynamic: classifier
Dynamic: license-file
Dynamic: requires-dist
Dynamic: requires-python
Dynamic: summary
